[
  {
    "text": "Evaluate `sin 0`",
    "skillId": "evaluating_sine",
    "acceptedAnswers": ["0"]
  },
  {
    "text": "Evaluate `sin(pi/6)`",
    "skillId": "evaluating_sine",
    "acceptedAnswers": ["1/2"]
  },
  {
    "text": "Evaluate `sin(pi/4)`",
    "skillId": "evaluating_sine",
    "acceptedAnswers": ["sqrt2/2"]
  },
  {
    "text": "Evaluate `sin(pi/3)`",
    "skillId": "evaluating_sine",
    "acceptedAnswers": ["sqrt3/2"]
  },
  {
    "text": "Evaluate `sin(pi/2)`",
    "skillId": "evaluating_sine",
    "acceptedAnswers": ["1"]
  },
  {
    "text": "Evaluate `sin((2pi)/3)`",
    "skillId": "evaluating_sine",
    "acceptedAnswers": ["sqrt3/2"]
  },
  {
    "text": "Evaluate `sin((3pi)/4)`",
    "skillId": "evaluating_sine",
    "acceptedAnswers": ["sqrt2/2"]
  },
  {
    "text": "Evaluate `sin((5pi)/6)`",
    "skillId": "evaluating_sine",
    "acceptedAnswers": ["1/2"]
  },
  {
    "text": "Evaluate `sin pi`",
    "skillId": "evaluating_sine",
    "acceptedAnswers": ["0"]
  },
  {
    "text": "Evaluate `sin((7pi)/6)`",
    "skillId": "evaluating_sine",
    "acceptedAnswers": ["-1/2"]
  },
  {
    "text": "Evaluate `sin((5pi)/4)`",
    "skillId": "evaluating_sine",
    "acceptedAnswers": ["-sqrt2/2"]
  },
  {
    "text": "Evaluate `sin((4pi)/3)`",
    "skillId": "evaluating_sine",
    "acceptedAnswers": ["-sqrt3/2"]
  },
  {
    "text": "Evaluate `sin((3pi)/2)`",
    "skillId": "evaluating_sine",
    "acceptedAnswers": ["-1"]
  },
  {
    "text": "Evaluate `sin((5pi)/3)`",
    "skillId": "evaluating_sine",
    "acceptedAnswers": ["-sqrt3/2"]
  },
  {
    "text": "Evaluate `sin((7pi)/4)`",
    "skillId": "evaluating_sine",
    "acceptedAnswers": ["-sqrt2/2"]
  },
  {
    "text": "Evaluate `sin((11pi)/6)`",
    "skillId": "evaluating_sine",
    "acceptedAnswers": ["-1/2"]
  },
  {
    "text": "Evaluate `sin(2pi)`",
    "skillId": "evaluating_sine",
    "acceptedAnswers": ["0"]
  },
  {
    "text": "Evaluate `cos 0`",
    "skillId": "evaluating_cosine",
    "acceptedAnswers": ["1"]
  },
  {
    "text": "Evaluate `cos(pi/6)`",
    "skillId": "evaluating_cosine",
    "acceptedAnswers": ["sqrt3/2"]
  },
  {
    "text": "Evaluate `cos(pi/4)`",
    "skillId": "evaluating_cosine",
    "acceptedAnswers": ["sqrt2/2"]
  },
  {
    "text": "Evaluate `cos(pi/3)`",
    "skillId": "evaluating_cosine",
    "acceptedAnswers": ["1/2"]
  },
  {
    "text": "Evaluate `cos(pi/2)`",
    "skillId": "evaluating_cosine",
    "acceptedAnswers": ["0"]
  },
  {
    "text": "Evaluate `cos((2pi)/3)`",
    "skillId": "evaluating_cosine",
    "acceptedAnswers": ["-1/2"]
  },
  {
    "text": "Evaluate `cos((3pi)/4)`",
    "skillId": "evaluating_cosine",
    "acceptedAnswers": ["-sqrt2/2"]
  },
  {
    "text": "Evaluate `cos((5pi)/6)`",
    "skillId": "evaluating_cosine",
    "acceptedAnswers": ["-sqrt3/2"]
  },
  {
    "text": "Evaluate `cos pi`",
    "skillId": "evaluating_cosine",
    "acceptedAnswers": ["-1"]
  },
  {
    "text": "Evaluate `cos((7pi)/6)`",
    "skillId": "evaluating_cosine",
    "acceptedAnswers": ["-sqrt3/2"]
  },
  {
    "text": "Evaluate `cos((5pi)/4)`",
    "skillId": "evaluating_cosine",
    "acceptedAnswers": ["-sqrt2/2"]
  },
  {
    "text": "Evaluate `cos((4pi)/3)`",
    "skillId": "evaluating_cosine",
    "acceptedAnswers": ["-1/2"]
  },
  {
    "text": "Evaluate `cos((3pi)/2)`",
    "skillId": "evaluating_cosine",
    "acceptedAnswers": ["0"]
  },
  {
    "text": "Evaluate `cos((5pi)/3)`",
    "skillId": "evaluating_cosine",
    "acceptedAnswers": ["1/2"]
  },
  {
    "text": "Evaluate `cos((7pi)/4)`",
    "skillId": "evaluating_cosine",
    "acceptedAnswers": ["sqrt2/2"]
  },
  {
    "text": "Evaluate `cos((11pi)/6)`",
    "skillId": "evaluating_cosine",
    "acceptedAnswers": ["sqrt3/2"]
  },
  {
    "text": "Evaluate `cos(2pi)`",
    "skillId": "evaluating_cosine",
    "acceptedAnswers": ["1"]
  },
  {
    "text": "Evaluate `tan 0`",
    "skillId": "evaluating_tangent",
    "acceptedAnswers": ["0"]
  },
  {
    "text": "Evaluate `tan(pi/6)`",
    "skillId": "evaluating_tangent",
    "acceptedAnswers": ["sqrt3/3"]
  },
  {
    "text": "Evaluate `tan(pi/4)`",
    "skillId": "evaluating_tangent",
    "acceptedAnswers": ["1"]
  },
  {
    "text": "Evaluate `tan(pi/3)`",
    "skillId": "evaluating_tangent",
    "acceptedAnswers": ["sqrt3"]
  },
  {
    "text": "Evaluate `tan(pi/2)`",
    "skillId": "evaluating_tangent",
    "acceptedAnswers": ["undefined"]
  },
  {
    "text": "Evaluate `tan((2pi)/3)`",
    "skillId": "evaluating_tangent",
    "acceptedAnswers": ["-sqrt3"]
  },
  {
    "text": "Evaluate `tan((3pi)/4)`",
    "skillId": "evaluating_tangent",
    "acceptedAnswers": ["-1"]
  },
  {
    "text": "Evaluate `tan((5pi)/6)`",
    "skillId": "evaluating_tangent",
    "acceptedAnswers": ["-sqrt3/3"]
  },
  {
    "text": "Evaluate `tan pi`",
    "skillId": "evaluating_tangent",
    "acceptedAnswers": ["0"]
  },
  {
    "text": "Evaluate `tan((7pi)/6)`",
    "skillId": "evaluating_tangent",
    "acceptedAnswers": ["sqrt3/3"]
  },
  {
    "text": "Evaluate `tan((5pi)/4)`",
    "skillId": "evaluating_tangent",
    "acceptedAnswers": ["1"]
  },
  {
    "text": "Evaluate `tan((4pi)/3)`",
    "skillId": "evaluating_tangent",
    "acceptedAnswers": ["sqrt3"]
  },
  {
    "text": "Evaluate `tan((3pi)/2)`",
    "skillId": "evaluating_tangent",
    "acceptedAnswers": ["undefined"]
  },
  {
    "text": "Evaluate `tan((5pi)/3)`",
    "skillId": "evaluating_tangent",
    "acceptedAnswers": ["-sqrt3"]
  },
  {
    "text": "Evaluate `tan((7pi)/4)`",
    "skillId": "evaluating_tangent",
    "acceptedAnswers": ["-1"]
  },
  {
    "text": "Evaluate `tan((11pi)/6)`",
    "skillId": "evaluating_tangent",
    "acceptedAnswers": ["-sqrt3/3"]
  },
  {
    "text": "Evaluate `tan(2pi)`",
    "skillId": "evaluating_tangent",
    "acceptedAnswers": ["0"]
  },
  {
    "text": "Evaluate `sin(pi/12)`",
    "skillId": "sine_compound_angle_identity",
    "acceptedAnswers": ["(sqrt3-1)/(2sqrt2)"]
  },
  {
    "text": "Find the least common denominator of `1/3`, `5/6` and `7/9`.",
    "skillId": "least_common_denominator",
    "acceptedAnswers": ["18"]
  },
  {
    "text": "Find the least common denominator of `1/2`, `2/3` and `5/7`.",
    "skillId": "least_common_denominator",
    "acceptedAnswers": ["42"]
  },
  {
    "text": "Find the least common denominator of `1/2`, `2/5`, `11/12` and `13/15`.",
    "skillId": "least_common_denominator",
    "acceptedAnswers": ["60"]
  },
  {
    "text": "Find the least common denominator of `1/2` and `2/3`.",
    "skillId": "least_common_denominator",
    "acceptedAnswers": ["6"]
  },
  {
    "text": "Find the least common denominator of `1/3` and `4/5`.",
    "skillId": "least_common_denominator",
    "acceptedAnswers": ["15"]
  },
  {
    "text": "Find the least common denominator of `1/2`, `4/3` and `2/5`.",
    "skillId": "least_common_denominator",
    "acceptedAnswers": ["30"]
  },
  {
    "text": "Find the least common denominator of `1/3` and `5/6`.",
    "skillId": "least_common_denominator",
    "acceptedAnswers": ["6"]
  },
  {
    "text": "Find the least common denominator of `7/8` and `1/4`.",
    "skillId": "least_common_denominator",
    "acceptedAnswers": ["8"]
  },
  {
    "text": "Find the least common denominator of `3/5`, `1/3` and `8/15`.",
    "skillId": "least_common_denominator",
    "acceptedAnswers": ["15"]
  },
  {
    "text": "Find the least common denominator of `5/8` and `7/12`.",
    "skillId": "least_common_denominator",
    "acceptedAnswers": ["24"]
  },
  {
    "text": "Find the least common denominator of `3/4`, `1/6` and `7/9`.",
    "skillId": "least_common_denominator",
    "acceptedAnswers": ["36"]
  },
  {
    "text": "Find the least common denominator of `5/6`, `7/9` and `11/15`.",
    "skillId": "least_common_denominator",
    "acceptedAnswers": ["90"]
  }
]
